cnpip/__init__.py
cnpip/cnpip.py
cnpip/mirrors.py
cnpip-1.2.2.dist-info/licenses/LICENSE
cnpip-1.2.2.dist-info/METADATA
cnpip-1.2.2.dist-info/WHEEL
cnpip-1.2.2.dist-info/entry_points.txt
cnpip-1.2.2.dist-info/top_level.txt
cnpip-1.2.2.dist-info/RECORD
