Metadata-Version: 2.4
Name: cnpip
Version: 1.2.2
Summary: 帮助中国用户快速切换 pip 镜像源，提升下载速度的命令行工具.
Home-page: https://github.com/caoergou/cnpip
Author: caoergou
Author-email: caoergou <mrjingcheng@foxmail.com>
Project-URL: Homepage, https://github.com/caoergou/cnpip
Project-URL: Issues, https://github.com/caoergou/cnpip/issues
Keywords: pip,mirror,Chinese,speed,cli
Classifier: License :: OSI Approved :: MIT License
Classifier: Intended Audience :: Developers
Classifier: Operating System :: OS Independent
Classifier: Programming Language :: Python :: 3
Classifier: Programming Language :: Python :: 3.6
Classifier: Programming Language :: Python :: 3.7
Classifier: Programming Language :: Python :: 3.8
Classifier: Programming Language :: Python :: 3.9
Classifier: Programming Language :: Python :: 3.10
Classifier: Programming Language :: Python :: 3.11
Classifier: Topic :: Software Development :: Libraries :: Python Modules
Classifier: Topic :: System :: Installation/Setup
Classifier: Topic :: Utilities
Requires-Python: >=3.7
License-File: LICENSE
Requires-Dist: requests
Provides-Extra: async
Requires-Dist: aiohttp; extra == "async"
Dynamic: author
Dynamic: home-page
Dynamic: license-file
